event_data_logging/__init__.py
event_data_logging/csv_writer.py
event_data_logging/data_handling.py
event_data_logging/file_handling.py
event_data_logging/json_writer.py
event_data_logging/ros2_message_handling.py
event_data_logging-0.1.4.dist-info/LICENSE
event_data_logging-0.1.4.dist-info/METADATA
event_data_logging-0.1.4.dist-info/WHEEL
event_data_logging-0.1.4.dist-info/top_level.txt
event_data_logging-0.1.4.dist-info/RECORD
