Metadata-Version: 2.1
Name: event-data-logging
Version: 0.1.4
Summary: Data writers with optional timestamps for logging of events
Home-page: https://github.com/maimonlab/event_data_logging
Author: Thomas Mohren
Author-email: tlmohren@gmail.com
License: MIT license
Classifier: Development Status :: 2 - Pre-Alpha
Classifier: Intended Audience :: Developers
Classifier: License :: OSI Approved :: MIT License
Classifier: Natural Language :: English
Classifier: Programming Language :: Python :: 3
Classifier: Programming Language :: Python :: 3.6
Classifier: Programming Language :: Python :: 3.7
Classifier: Programming Language :: Python :: 3.8
Requires-Python: >=3.6
License-File: LICENSE
Requires-Dist: numpy
Provides-Extra: test
Requires-Dist: pytest ; extra == 'test'
Requires-Dist: coverage ; extra == 'test'
